LICENSE.md
README.md
setup.py
ane_transformers/__init__.py
ane_transformers/_version.py
ane_transformers/testing_utils.py
ane_transformers.egg-info/PKG-INFO
ane_transformers.egg-info/SOURCES.txt
ane_transformers.egg-info/dependency_links.txt
ane_transformers.egg-info/requires.txt
ane_transformers.egg-info/top_level.txt
ane_transformers/huggingface/__init__.py
ane_transformers/huggingface/distilbert.py
ane_transformers/huggingface/test_distilbert.py
ane_transformers/reference/__init__.py
ane_transformers/reference/decoder.py
ane_transformers/reference/encoder.py
ane_transformers/reference/ffn.py
ane_transformers/reference/layer_norm.py
ane_transformers/reference/multihead_attention.py
ane_transformers/reference/test_transformer.py
ane_transformers/reference/transformer.py