Metadata-Version: 2.1
Name: ane-transformers
Version: 0.1.3
Summary: Reference PyTorch implementation of Transformers for Apple Neural Engine (ANE) deployment
Home-page: https://github.com/apple/ml-ane-transformers
Author: Apple Inc.
License: UNKNOWN
Platform: UNKNOWN
Classifier: Development Status :: 4 - Beta
Classifier: Intended Audience :: Developers
Classifier: Operating System :: MacOS :: MacOS X
Classifier: Operating System :: POSIX :: Linux
Classifier: Programming Language :: Python :: 3.5
Classifier: Programming Language :: Python :: 3.6
Classifier: Programming Language :: Python :: 3.7
Classifier: Programming Language :: Python :: 3.8
Classifier: Programming Language :: Python :: 3.9
Classifier: Topic :: Scientific/Engineering
Classifier: Topic :: Software Development
License-File: LICENSE.md
